empirica_crm/__init__.py
empirica_crm/client_memory.py
empirica_crm/client_store.py
empirica_crm/engagement_store.py
empirica_crm/epistemic_metrics.py
empirica_crm/interaction_store.py
empirica_crm/memory_backend.py
empirica_crm/notebooklm.py
empirica_crm/schema.py
empirica_crm/cli/__init__.py
empirica_crm/cli/_utils.py
empirica_crm/cli/client_handlers.py
empirica_crm/cli/commands.py
empirica_crm/cli/engagement_handlers.py
empirica_crm/cli/interaction_handlers.py
empirica_crm/cli/memory_handlers.py
empirica_crm/cli/metrics_handlers.py
empirica_crm/cli/notebook_handlers.py
empirica_crm/tests/__init__.py
empirica_crm/tests/conftest.py
empirica_crm/tests/test_client_store.py
empirica_crm/tests/test_engagement_store.py
empirica_crm/tests/test_epistemic_metrics.py
empirica_crm/tests/test_interaction_store.py
empirica_crm/tests/test_memory_backend.py
empirica_crm-0.1.0.dist-info/licenses/LICENSE
empirica_crm-0.1.0.dist-info/METADATA
empirica_crm-0.1.0.dist-info/WHEEL
empirica_crm-0.1.0.dist-info/entry_points.txt
empirica_crm-0.1.0.dist-info/top_level.txt
empirica_crm-0.1.0.dist-info/RECORD
