Metadata-Version: 2.4
Name: empirica-crm
Version: 0.1.0
Summary: CRM module for Empirica - Client Relationship Management with epistemic tracking
Author: David S. L. van Assche
License: BSL-1.1
Keywords: empirica,crm,ai,epistemics,client-management
Classifier: Development Status :: 3 - Alpha
Classifier: Intended Audience :: Developers
Classifier: License :: Other/Proprietary License
Classifier: Programming Language :: Python :: 3
Classifier: Programming Language :: Python :: 3.10
Classifier: Programming Language :: Python :: 3.11
Classifier: Programming Language :: Python :: 3.12
Requires-Python: >=3.10
License-File: LICENSE
Requires-Dist: empirica>=1.2.4
Provides-Extra: dev
Requires-Dist: pytest>=7.0; extra == "dev"
Requires-Dist: pytest-cov>=4.0; extra == "dev"
Dynamic: license-file
